pycaptureautomation/__init__.py
pycaptureautomation/capturearea.py
pycaptureautomation/circle.py
pycaptureautomation/color.py
pycaptureautomation/mask.py
pycaptureautomation/pycaptureautomation.py
pycaptureautomation/rectangle.py
pycaptureautomation-0.1.5.dist-info/LICENSE
pycaptureautomation-0.1.5.dist-info/METADATA
pycaptureautomation-0.1.5.dist-info/WHEEL
pycaptureautomation-0.1.5.dist-info/top_level.txt
pycaptureautomation-0.1.5.dist-info/RECORD
